xapp_adapta/README.md
xapp_adapta/__init__.py
xapp_adapta/__main__.py
xapp_adapta/adapta_main.py
xapp_adapta/adapta_test.py
xapp_adapta/domain.txt
xapp_adapta/applications/adapta_main.desktop
xapp_adapta/icons/hicolor/scalable/apps/com.github.jackokring.adapta_main.svg
xapp_adapta/locale/LC_MESSAGES/messages/com.github.jackokring.xapp_adapta.mo
xapp_adapta/xapp/__init__.py
xapp_adapta/xapp/os.py
xapp_adapta-0.0.7.dist-info/METADATA
xapp_adapta-0.0.7.dist-info/WHEEL
xapp_adapta-0.0.7.dist-info/entry_points.txt
xapp_adapta-0.0.7.dist-info/RECORD
