Metadata-Version: 2.4
Name: xapp_adapta
Version: 0.0.7
Summary: Python libAdapta
Project-URL: Homepage, https://github.com/jackokring/mint-python-adapta
Project-URL: Bug Tracker, https://github.com/jackokring/mint-python-adapta/issues
Author: Linux Mint Team, GNOME Adwaita Team, All Di Nice
Author-email: Simon Jackson <jackokring@gmail.com>
Classifier: License :: OSI Approved :: GNU Lesser General Public License v3 (LGPLv3)
Classifier: Operating System :: OS Independent
Classifier: Programming Language :: Python :: 3
Requires-Python: >=3.12
Requires-Dist: hatch>=1.14.1
Requires-Dist: hatchling>=1.27.0
Requires-Dist: pycairo>=1.28.0
Requires-Dist: pygobject-stubs>=2.13.0
Requires-Dist: pygobject>=3.52.3
